{    "type": "gsd","names":{"Fax_No":"N.° de fax","Site_ID":"ID del sitio","Site_Name":"Nombre del sitio","Site_Status_Short_Desc":"Estado del sitio","Telephone_Country_Code":"Código telefónico del país","Telephone_no":"N.° telefónico","Territory_Short_Desc":"Nombre del territorio o provincia","City_Name":"Nombre de la ciudad","Country_Code":"Código del país","Country_Name":"País","Postal_Code":"Código postal","Site_Address":"Dirección del sitio","Latitude_No":"Latitud","Longitude_No":"Longitud","Site_Shop_Format_Name":"Nombre de la expendedora del sitio","Loyalty_Program_Ind":"Indicador de programa de fidelización","Trading_Hours_Qty":"Cantidad de horas de atención","Site_Car_Wash_Type_Name":"Tipo de lavadero de autos del sitio","Site_Car_Wash_Type":"Tipo de lavadero de autos del sitio","Site_ATM_Service_Type_Name":"Tipo de cajero automático del sitio","Site_ATM_Service_Type":"Tipo de cajero automático del sitio","Site Restaurant Type Name ":"Tipo de restaurante del sitio","Site_Restaurant_Type_Name":"Tipo de restaurante del sitio","Site_Restaurant_Type":"Tipo de restaurante del sitio","Air & Water":"Aire y agua","ATM":"Cajero automático","Automotive LPG":"GLP para automóviles","Bakery Shop":"Panadería","Bank note acceptor":"Cajero de depósitos","Bar":"Bar","Bottled Gas":"Gas envasado","Canopy":"Toldo","Car rental":"Alquiler de autos","Car Wash":"Lavadero de autos","Wifi":"Wifi","Credit cards":"Tarjetas de crédito","External Card Reader":"Lector de tarjetas externo","Facilities for disabled":"Instalaciones para personas con discapacidad","Fast Food - Food Service":"Comida rápida - Servicio de comidas","Fast-food Counter- attended":"Mostrador de comida rápida - con servicio","Fuel cards":"Tarjetas de combustibles","HGV Lane":"Carril para vehículos pesados","Lottery":"Lotería","Parking Place":"Estacionamiento","Paypoint":"Punto de pago","Service Bay":"Área de mantenimiento","Third party rental":"Alquileres de terceros","Transponder":"Transpondedor","Truckport":"Acceso para camiones","Two-stroke pre-mix":"Premezcla para motores dos tiempos","Vacuum":"Aspiradora","Water Closet or Toilet":"Baños","CRT (Commerical Road Transportation)":"CRT (Commerical Road Transportation)","Toll Vignettes":"Viñetas de peaje","Partner Loyalty Accepted":"Socio de fidelización aceptado","Food Offerings":"Oferta de comidas","Max Vehicle size Access":"Tamaño máximo de vehículo","Discount":"Descuento","Fuel Service":"Servicio de combustible","Co Locator":"Co Locator","Shower":"Ducha","Vehicle Identity System":"Sistema de identificación de vehículo","Transportation Service":"Servicio de transporte","Quick Lubes":"Lubricantes rápidos","High Speed Diesel Pump":"Bomba diésel de alta velocidad","Fleet cards":"Tarjetas de flota","Loyalty cards":"Tarjetas de Fidelidad","Type of Parking":"Tipo de Estacionamiento","Organisational_Affiliation_Type_Code":"Bandera","Organisational_Affiliation_Code":"Afiliación organizacional","Site_Status_Code":"Estado del Sitio","Visibility_Score_No":"Puntuación Visibilidad","Accessibility_Score_No":"Puntuación Accesibilidad", "Traffic_flow_score_No":"Puntación Flujo de Tránsito","ROAD_TYPE_CODE":"Tipo de Calle", "Buying_Area_Score_No":"Puntuación Area de Compra","Site_Closing_Date":"Fecha cierre Sitio ","Site_Opening_Date":" Fecha apertura Sitio","24 Hour Fuel Service":"Servicio 24 hs."},"values":{"Ad Blue Pump Truck":"Ad Blue Pump Truck","Ad Blue Pump Passenger Vehicles":"Ad Blue Pump Passenger Vehicles","Ad Blue Packed Product":"Ad Blue Packed Product","Shell Shop":"Shell Shop","Select":"Seleccionar","Other":"Otro"," No hay comercio":" No hay comercio","SELF":"Autoservicio","ATTENDED":"Atendido","CO":"Franquicia de marca compartida","NONE":" Ninguno","JET":"Lavado Jet","ROLLOVER":"Lavado con rodillo","CONVEYOR":"Lavado con cinta transportadora","MANUAL":"Lavado manual","None":"Ninguno","ATM-IN":"Cajero automático en el interior de la tienda","ATM-OUT":"Cajero automático en el exterior de la tienda","DKV":"DKV","UTA":"UTA","Esso":"Esso","Eni":"Eni","Club Smart":"Club Smart","Shell Club Smart Extra Card":"Shell Club Smart Extra Card","Costa Express":"Costa Express","DeliToGo":"DeliToGo","2TheLoo":"2TheLoo","KFC":"KFC","McDonald":"McDonald's","Brazilian Cafe (TBC)":"Brazilian Cafe (TBC)","Steer Diner":"Steer Diner","MAXI's":"MAXI's","Steers":"Steers","Austrian Highway Sticker":"Viñeta de autopista autstríaca","Czech Highway Sticker":"Viñeta de autopista checa","Slovak Highway Sticker":"Viñeta de autopista de Eslovaquia","Hungarian Highway Sticker":"Viñeta de autopista húngara","KROGER":"KROGER","SMITHS":"SMITHS","FRED MEYER MP":"FRED MEYER MP","GIANT FOODS":"GIANT FOODS","DILLONS":"DILLONS","JAY C":"JAY C","KING SOOPERS":"KING SOOPERS","CITY MARKET":"CITY MARKET","PAYLESS":"PAYLESS","SCOTT'S":"SCOTT'S","OWENS":"OWENS","WINN DIXIE":"WINN DIXIE","HILANDER":"HILANDER","SMITH'S MP":"SMITH'S MP","BiLo":"BiLo","STOP AND SHOP":"STOP AND SHOP","QFC":"QFC","FREDY MEYER":"FREDY MEYER","RALPHS FRESH FAYRE":"RALPHS FRESH FAYRE","Save Mart":"Save Mart","FRY'S":"FRY'S","Snack Food":"Refrigerios","Sandwich":"Sándwich","Burger":"Hamburguesa","Pizza":"Pizza","Hot Food":"Comida caliente","Coffee":"Café","Restaurant":"Restaurante","Semi trailer":"Semi trailer","Semi-Trailer - Bdouble":"Semi-Trailer - Bdouble","RoadTrain":"RoadTrain","Telepass Premium":"Telepass Premium","Sconti BancoPosta":"Sconti BancoPosta","Supermarket Fuel Discount":"Supermarket Fuel Discount","Full service":"Full service","Motorway service":"Motorway service","Unmanned":"Estación automática","Ido ticket":"Ido ticket","Touch & Go":"Touch & Go","Maut Terminal":"Maut Terminal","Parking lanes":"Carriles de estacionamiento","Guarded car park":"Estacionamiento con custodia","Truck parking":"Estacionamiento para camiones","Credit card - General":"Tarjeta de crédito - General","Shell card":"Tarjeta Shell","EuroShell card":"Tarjeta EuroShell","Partner Card":"Tarjeta de socio","Fleet card - General":"Tarjeta de flota - General","Shell V-Power Club":"Shell V-Power Club","Bonuslink":"Bonuslink","Others":"Otros","Tim Hortons":"Tim Hortons","Australian Highway Sticker":"Viñeta de autopista australiana","JEWEL":"JEWEL","ROUNDY'S":"ROUNDY'S","Cafe":"Café","Dockside Fueling":"Dársena de carga","Self service":"Autoservicio","Credit card - Visa":"Tarjetas de crédito - Visa","Credit card - Mastercard":"Tarjetas de crédito - Mastercard","Credit card - American Express":"Tarjetas de crédito - American Express","Credit card - Diners Club":"Tarjetas de crédito - Diners Club","Loyalty cards":"Tarjetas de Fidelidad","Ecotax Service":"Servicio Ecotax","Bdouble":"Bdouble"}}
